{
    "market_trend": "gained roughly 0.09%",
    "sectors_jumped": [
        "Financials (XLF) (+1.04%)"
    ],
    "sectors_dipped": [
        "Technology (XLK) (-0.05%)",
        "Energy (XLE) (-0.09%)",
        "Healthcare (XLV) (-0.93%)"
    ],
    "top_etf": "S-C-H-D",
    "daily_voiceover_script": "The stock market just wrapped another major trading session. The S&P 500 nudged up 0.09% today, but the *real* story was a massive internal rotation. While the headline looked flat, capital was moving. Financials *soared* over 1%, signaling renewed confidence and interest-rate optimism. Meanwhile, Technology, Energy, and Healthcare all saw dips \u2013 investors taking profits, re-evaluating, and cycling out of recent high-flyers. This isn't chaos; it's smart money rebalancing. Understand this: daily ups and downs are normal market breathing. Panic-selling a dip or chasing every green jump is the fastest way to *destroy* your long-term wealth. Stop reacting, start building. Ignore the short-term noise. Instead, auto-compound your cash into proven long-term vehicles like S-C-H-D. Let dividends do the heavy lifting. Head over to the link in my bio, grab my free Low-Anxiety Investing Blueprint, and let's automate your wealth building today."
}