{
    "last_updated": "2026-07-23 09:30 PM EST",
    "market_vibe": "Bearish",
    "market_data": {
        "S&P 500": {
            "ticker": "SPY",
            "price": 738.18,
            "change": -1.23
        },
        "Nasdaq": {
            "ticker": "QQQ",
            "price": 691.96,
            "change": -1.9
        },
        "XRP": {
            "ticker": "XRP-USD",
            "price": 1.11,
            "change": -2.79
        }
    },
    "daily_script": "What's the market *vibe* today? Alright, if you're building a long-term bag, let\u2019s keep it chill. We're seeing some red across the board, but zero panic. SPY and QQQ, your usual market movers, are dipping a bit, taking a breather. Even XRP is cooling off a touch.\n\nThink of it as the market hitting the pause button, not the eject button. These days are just part of the ride when you\u2019re playing the long game. Don't stress the daily swings; focus on the consistent growth.\n\nWant to track this stress-free? Hit the pinned link for our free, no-nonsense market terminal."
}